pydantic_fetch/__init__.py
pydantic_fetch/basemodel.py
pydantic_fetch-0.0.3.dist-info/METADATA
pydantic_fetch-0.0.3.dist-info/WHEEL
pydantic_fetch-0.0.3.dist-info/top_level.txt
pydantic_fetch-0.0.3.dist-info/RECORD
