Metadata-Version: 2.1
Name: pydantic-fetch
Version: 0.0.3
Summary: Extension of pydantic models for HTTP send/recieve
Home-page: https://github.com/bayinfosys/pydantic-fetch
Author: ed
Author-email: ed@bayis.co.uk
Classifier: Programming Language :: Python :: 3
Classifier: Operating System :: OS Independent
Requires-Python: >=3.6
Requires-Dist: pydantic
Provides-Extra: httpx
Requires-Dist: httpx ; extra == 'httpx'
Provides-Extra: tests
Requires-Dist: mock ; extra == 'tests'
Requires-Dist: pytest ; extra == 'tests'
